curv_amqp/__init__.py
curv_amqp/channel.py
curv_amqp/conditional_reconnect.py
curv_amqp/connection.py
curv_amqp/consumer.py
curv_amqp/exceptions.py
curv_amqp/inactivity_timeout.py
curv_amqp/mocks.py
curv_amqp/publisher.py
curv_amqp/timestamp.py
tests/__init__.py
tests/main.py
curv_amqp-1.3.7.dist-info/LICENSE
curv_amqp-1.3.7.dist-info/METADATA
curv_amqp-1.3.7.dist-info/WHEEL
curv_amqp-1.3.7.dist-info/top_level.txt
curv_amqp-1.3.7.dist-info/RECORD
