Metadata-Version: 2.1
Name: curv-amqp
Version: 1.3.7
Summary: UNKNOWN
Home-page: http://github.com/rep-ai/curv_amqp
License: MIT
Platform: UNKNOWN
Requires-Dist: pika
Requires-Dist: simplejson
Requires-Dist: arrow
